MANIFEST.in
README.md
setup.py
cerastes/__init__.py
cerastes/channel.py
cerastes/client.py
cerastes/cmdtool.py
cerastes/config.py
cerastes/controller.py
cerastes/errors.py
cerastes/kerberos.py
cerastes/proto_utils.py
cerastes/rpc_sasl.py
cerastes/utils.py
cerastes.egg-info/PKG-INFO
cerastes.egg-info/SOURCES.txt
cerastes.egg-info/dependency_links.txt
cerastes.egg-info/entry_points.txt
cerastes.egg-info/requires.txt
cerastes.egg-info/top_level.txt
cerastes/protobuf/HAServiceProtocol_pb2.py
cerastes/protobuf/HSAdminRefreshProtocol_pb2.py
cerastes/protobuf/IpcConnectionContext_pb2.py
cerastes/protobuf/MRClientProtocol_pb2.py
cerastes/protobuf/ProtobufRpcEngine_pb2.py
cerastes/protobuf/ResourceTracker_pb2.py
cerastes/protobuf/RpcHeader_pb2.py
cerastes/protobuf/Security_pb2.py
cerastes/protobuf/__init__.py
cerastes/protobuf/application_history_client_pb2.py
cerastes/protobuf/application_history_server_pb2.py
cerastes/protobuf/applicationclient_protocol_pb2.py
cerastes/protobuf/applicationmaster_protocol_pb2.py
cerastes/protobuf/containermanagement_protocol_pb2.py
cerastes/protobuf/mr_protos_pb2.py
cerastes/protobuf/mr_service_protos_pb2.py
cerastes/protobuf/resourcemanager_administration_protocol_pb2.py
cerastes/protobuf/yarn_protos_pb2.py
cerastes/protobuf/yarn_server_common_protos_pb2.py
cerastes/protobuf/yarn_server_common_service_protos_pb2.py
cerastes/protobuf/yarn_server_resourcemanager_service_protos_pb2.py
cerastes/protobuf/yarn_service_protos_pb2.py
cerastes/resources/__init__.py
cerastes/resources/config_schema.json