Metadata-Version: 1.1
Name: cerastes
Version: 1.1.0
Summary: UNKNOWN
Home-page: https://github.com/yassineazzouz/cerastes
Author: Yassine Azzouz
Author-email: yassine.azzouz@agmail.com
License: GPLv3
Platform: UNKNOWN
Classifier: Development Status :: 5 - Production/Stable
Classifier: Intended Audience :: Developers
Classifier: Intended Audience :: System Administrators
Classifier: License :: OSI Approved :: GNU General Public License v3 or later (GPLv3+)
Classifier: Operating System :: POSIX
Classifier: Programming Language :: Python
Classifier: Programming Language :: Python :: 2.6
Classifier: Programming Language :: Python :: 2.7
Classifier: Programming Language :: Python :: 3.3
Classifier: Programming Language :: Python :: 3.4
